{
  "modelVersion" : "2.2",
  "id" : "PSGRCatPuestoTrabajo",
  "name" : "PSGRCatPuestoTrabajo",
  "lastUpdate" : 1701897854287,
  "rows" : [
    [
      {
        "type" : "component",
        "dimension" : {
          "xs" : 12,
          "sm" : 12,
          "md" : 12,
          "lg" : 12
        },
        "propertyValues" : {
          "cssClasses" : {
            "type" : "constant",
            "value" : ""
          },
          "hidden" : {
            "type" : "constant",
            "value" : false
          },
          "srcType" : {
            "type" : "constant",
            "value" : "URL"
          },
          "url" : {
            "type" : "constant"
          },
          "assetName" : {
            "type" : "constant"
          },
          "alt" : {
            "type" : "interpolation",
            "value" : "Catálogo puesto de trabajo"
          }
        },
        "reference" : "de5efc94-7156-482d-8569-4d96aa888e0b",
        "hasValidationError" : false,
        "id" : "customPSGRWidgetHeader"
      }
    ],
    [
      {
        "type" : "container",
        "dimension" : {
          "xs" : 12,
          "sm" : 1,
          "md" : 1,
          "lg" : 2
        },
        "propertyValues" : {
          "cssClasses" : {
            "type" : "constant",
            "value" : ""
          },
          "hidden" : {
            "type" : "constant",
            "value" : false
          },
          "repeatedCollection" : {
            "type" : "variable",
            "value" : ""
          }
        },
        "reference" : "4a2387f0-560d-4531-bc36-5ac15eb16ba7",
        "hasValidationError" : false,
        "id" : "pbContainer",
        "rows" : [
          [ ]
        ]
      },
      {
        "type" : "container",
        "dimension" : {
          "xs" : 12,
          "sm" : 10,
          "md" : 10,
          "lg" : 8
        },
        "propertyValues" : {
          "cssClasses" : {
            "type" : "constant",
            "value" : ""
          },
          "hidden" : {
            "type" : "constant",
            "value" : false
          },
          "repeatedCollection" : {
            "type" : "variable",
            "value" : ""
          }
        },
        "reference" : "9df2eff9-bc15-469b-aa3a-a9271e768770",
        "hasValidationError" : false,
        "id" : "pbContainer",
        "rows" : [
          [
            {
              "type" : "component",
              "dimension" : {
                "xs" : 12,
                "sm" : 12,
                "md" : 12,
                "lg" : 12
              },
              "propertyValues" : {
                "cssClasses" : {
                  "type" : "constant",
                  "value" : "color-orange"
                },
                "hidden" : {
                  "type" : "constant",
                  "value" : true
                },
                "text" : {
                  "type" : "interpolation",
                  "value" : "Catalogo puesto trabajo"
                },
                "level" : {
                  "type" : "constant",
                  "value" : "Level 3"
                },
                "alignment" : {
                  "type" : "constant",
                  "value" : "center"
                }
              },
              "reference" : "d04dba6b-9c04-425b-8cad-e3e273e1b763",
              "hasValidationError" : false,
              "id" : "pbTitle"
            }
          ],
          [
            {
              "type" : "component",
              "dimension" : {
                "xs" : 12,
                "sm" : 12,
                "md" : 12,
                "lg" : 12
              },
              "propertyValues" : {
                "cssClasses" : {
                  "type" : "constant",
                  "value" : ""
                },
                "hidden" : {
                  "type" : "constant",
                  "value" : true
                },
                "labelHidden" : {
                  "type" : "constant",
                  "value" : true
                },
                "label" : {
                  "type" : "interpolation",
                  "value" : "Default label"
                },
                "labelPosition" : {
                  "type" : "constant",
                  "value" : "top"
                },
                "labelWidth" : {
                  "type" : "constant",
                  "value" : 4
                },
                "allowHTML" : {
                  "type" : "constant",
                  "value" : true
                },
                "text" : {
                  "type" : "interpolation",
                  "value" : "<hr>"
                },
                "alignment" : {
                  "type" : "constant",
                  "value" : "left"
                }
              },
              "reference" : "c21836ab-645e-4455-a662-0d66c0b834e3",
              "hasValidationError" : false,
              "id" : "pbText"
            }
          ],
          [
            {
              "type" : "component",
              "dimension" : {
                "xs" : 12,
                "sm" : 12,
                "md" : 12,
                "lg" : 12
              },
              "propertyValues" : {
                "cssClasses" : {
                  "type" : "constant",
                  "value" : ""
                },
                "hidden" : {
                  "type" : "expression",
                  "value" : "navigationVar !== \"tabla\""
                },
                "disabled" : {
                  "type" : "constant",
                  "value" : false
                },
                "label" : {
                  "type" : "interpolation",
                  "value" : "<span class=\"glyphicon glyphicon-plus\"></span> Agregar"
                },
                "alignment" : {
                  "type" : "constant",
                  "value" : "right"
                },
                "buttonStyle" : {
                  "type" : "constant",
                  "value" : "primary"
                },
                "action" : {
                  "type" : "constant",
                  "value" : "Submit task"
                },
                "navigationVar" : {
                  "type" : "variable",
                  "value" : "navigationVar"
                },
                "newValue" : {
                  "type" : "constant",
                  "value" : "nuevo"
                },
                "objetoCat" : {
                  "type" : "variable",
                  "value" : "selectedCat"
                }
              },
              "reference" : "8fdb73bf-5491-420f-ab70-cfd4c9c1e7ff",
              "hasValidationError" : false,
              "id" : "customPSGRbtnReiniciarCatNavegar"
            }
          ],
          [
            {
              "type" : "component",
              "dimension" : {
                "xs" : 12,
                "sm" : 12,
                "md" : 12,
                "lg" : 12
              },
              "propertyValues" : {
                "cssClasses" : {
                  "type" : "constant",
                  "value" : ""
                },
                "hidden" : {
                  "type" : "expression",
                  "value" : "navigationVar !== \"tabla\""
                },
                "allowHTML" : {
                  "type" : "constant",
                  "value" : true
                },
                "headers" : {
                  "type" : "constant",
                  "value" : [
                    "Orden",
                    "Clave",
                    "Descripcion"
                  ]
                },
                "content" : {
                  "type" : "variable",
                  "value" : "lstCat"
                },
                "columnsKey" : {
                  "type" : "constant",
                  "value" : [
                    "orden",
                    "clave",
                    "descripcion"
                  ]
                },
                "selectedRow" : {
                  "type" : "variable",
                  "value" : "selectedCat"
                },
                "striped" : {
                  "type" : "constant",
                  "value" : true
                },
                "condensed" : {
                  "type" : "constant",
                  "value" : false
                },
                "bordered" : {
                  "type" : "constant",
                  "value" : false
                },
                "urlGet" : {
                  "type" : "constant",
                  "value" : "../API/extension/posgradosRest?url=getCatPuestoTrabajo"
                },
                "reload" : {
                  "type" : "variable",
                  "value" : "reload"
                },
                "navigationVar" : {
                  "type" : "variable",
                  "value" : "navigationVar"
                },
                "urlDelete" : {
                  "type" : "constant",
                  "value" : "../API/extension/posgradosRest?url=deleteCatPuestoTrabajo"
                }
              },
              "reference" : "b4fc1560-f2e1-428a-b48d-e5fca2624722",
              "hasValidationError" : false,
              "id" : "customPSGRTablaCatV3persistenceid"
            }
          ],
          [
            {
              "type" : "container",
              "dimension" : {
                "xs" : 12,
                "sm" : 12,
                "md" : 12,
                "lg" : 12
              },
              "propertyValues" : {
                "cssClasses" : {
                  "type" : "constant",
                  "value" : ""
                },
                "hidden" : {
                  "type" : "expression",
                  "value" : "navigationVar !== \"editar\" && navigationVar !== \"nuevo\""
                },
                "repeatedCollection" : {
                  "type" : "variable",
                  "value" : ""
                }
              },
              "reference" : "822d7cc7-4b3b-4e63-8c14-b93f8dc4e0bb",
              "hasValidationError" : false,
              "id" : "pbContainer",
              "rows" : [
                [
                  {
                    "type" : "component",
                    "dimension" : {
                      "xs" : 12,
                      "sm" : 12,
                      "md" : 4,
                      "lg" : 4
                    },
                    "propertyValues" : {
                      "cssClasses" : {
                        "type" : "constant",
                        "value" : ""
                      },
                      "hidden" : {
                        "type" : "constant",
                        "value" : false
                      },
                      "required" : {
                        "type" : "constant",
                        "value" : false
                      },
                      "minLength" : {
                        "type" : "constant",
                        "value" : ""
                      },
                      "maxLength" : {
                        "type" : "constant",
                        "value" : ""
                      },
                      "readOnly" : {
                        "type" : "constant",
                        "value" : false
                      },
                      "labelHidden" : {
                        "type" : "constant",
                        "value" : false
                      },
                      "label" : {
                        "type" : "interpolation",
                        "value" : "Orden"
                      },
                      "labelPosition" : {
                        "type" : "constant",
                        "value" : "top"
                      },
                      "labelWidth" : {
                        "type" : "constant",
                        "value" : 4
                      },
                      "placeholder" : {
                        "type" : "interpolation"
                      },
                      "value" : {
                        "type" : "variable",
                        "value" : "selectedCat.orden"
                      },
                      "type" : {
                        "type" : "constant",
                        "value" : "number"
                      },
                      "min" : {
                        "type" : "constant",
                        "value" : 0
                      },
                      "max" : {
                        "type" : "constant",
                        "value" : 99999
                      },
                      "step" : {
                        "type" : "constant",
                        "value" : 1
                      }
                    },
                    "reference" : "0a9e44f2-0359-4102-aa51-54f1f6a385e9",
                    "hasValidationError" : false,
                    "id" : "pbInput"
                  },
                  {
                    "type" : "component",
                    "dimension" : {
                      "xs" : 12,
                      "sm" : 12,
                      "md" : 4,
                      "lg" : 4
                    },
                    "propertyValues" : {
                      "cssClasses" : {
                        "type" : "constant",
                        "value" : ""
                      },
                      "hidden" : {
                        "type" : "constant",
                        "value" : false
                      },
                      "required" : {
                        "type" : "constant",
                        "value" : false
                      },
                      "minLength" : {
                        "type" : "constant",
                        "value" : ""
                      },
                      "maxLength" : {
                        "type" : "constant",
                        "value" : ""
                      },
                      "readOnly" : {
                        "type" : "constant",
                        "value" : false
                      },
                      "labelHidden" : {
                        "type" : "constant",
                        "value" : false
                      },
                      "label" : {
                        "type" : "interpolation",
                        "value" : "Clave"
                      },
                      "labelPosition" : {
                        "type" : "constant",
                        "value" : "top"
                      },
                      "labelWidth" : {
                        "type" : "constant",
                        "value" : 4
                      },
                      "placeholder" : {
                        "type" : "interpolation"
                      },
                      "value" : {
                        "type" : "variable",
                        "value" : "selectedCat.clave"
                      },
                      "type" : {
                        "type" : "constant",
                        "value" : "text"
                      },
                      "min" : {
                        "type" : "constant"
                      },
                      "max" : {
                        "type" : "constant"
                      },
                      "step" : {
                        "type" : "constant",
                        "value" : 1
                      }
                    },
                    "reference" : "b7264c25-a884-468f-a200-51814e703670",
                    "hasValidationError" : false,
                    "id" : "pbInput"
                  },
                  {
                    "type" : "component",
                    "dimension" : {
                      "xs" : 12,
                      "sm" : 12,
                      "md" : 4,
                      "lg" : 4
                    },
                    "propertyValues" : {
                      "cssClasses" : {
                        "type" : "constant",
                        "value" : ""
                      },
                      "hidden" : {
                        "type" : "constant",
                        "value" : false
                      },
                      "required" : {
                        "type" : "constant",
                        "value" : false
                      },
                      "minLength" : {
                        "type" : "constant",
                        "value" : ""
                      },
                      "maxLength" : {
                        "type" : "constant",
                        "value" : ""
                      },
                      "readOnly" : {
                        "type" : "constant",
                        "value" : false
                      },
                      "labelHidden" : {
                        "type" : "constant",
                        "value" : false
                      },
                      "label" : {
                        "type" : "interpolation",
                        "value" : "Descripcion"
                      },
                      "labelPosition" : {
                        "type" : "constant",
                        "value" : "top"
                      },
                      "labelWidth" : {
                        "type" : "constant",
                        "value" : 4
                      },
                      "placeholder" : {
                        "type" : "interpolation"
                      },
                      "value" : {
                        "type" : "variable",
                        "value" : "selectedCat.descripcion"
                      },
                      "type" : {
                        "type" : "constant",
                        "value" : "text"
                      },
                      "min" : {
                        "type" : "constant"
                      },
                      "max" : {
                        "type" : "constant"
                      },
                      "step" : {
                        "type" : "constant",
                        "value" : 1
                      }
                    },
                    "reference" : "0db4a936-a097-44a6-ae08-136ed1e64743",
                    "hasValidationError" : false,
                    "id" : "pbInput"
                  }
                ],
                [
                  {
                    "type" : "component",
                    "dimension" : {
                      "xs" : 12,
                      "sm" : 12,
                      "md" : 6,
                      "lg" : 6
                    },
                    "propertyValues" : {
                      "cssClasses" : {
                        "type" : "constant",
                        "value" : ""
                      },
                      "hidden" : {
                        "type" : "constant",
                        "value" : false
                      },
                      "disabled" : {
                        "type" : "constant",
                        "value" : false
                      },
                      "label" : {
                        "type" : "interpolation",
                        "value" : "Cancelar"
                      },
                      "alignment" : {
                        "type" : "constant",
                        "value" : "left"
                      },
                      "buttonStyle" : {
                        "type" : "constant",
                        "value" : "info"
                      },
                      "action" : {
                        "type" : "constant",
                        "value" : "Submit task"
                      },
                      "navigationVar" : {
                        "type" : "variable",
                        "value" : "navigationVar"
                      },
                      "newValue" : {
                        "type" : "constant",
                        "value" : "tabla"
                      }
                    },
                    "reference" : "5bb876ea-4df6-43ce-9435-b68f450189c8",
                    "hasValidationError" : false,
                    "id" : "customCustomBtnNavigationByVariable"
                  },
                  {
                    "type" : "component",
                    "dimension" : {
                      "xs" : 12,
                      "sm" : 12,
                      "md" : 6,
                      "lg" : 6
                    },
                    "propertyValues" : {
                      "cssClasses" : {
                        "type" : "constant",
                        "value" : ""
                      },
                      "hidden" : {
                        "type" : "constant",
                        "value" : false
                      },
                      "disabled" : {
                        "type" : "constant",
                        "value" : false
                      },
                      "label" : {
                        "type" : "interpolation",
                        "value" : "Guardar"
                      },
                      "alignment" : {
                        "type" : "constant",
                        "value" : "right"
                      },
                      "buttonStyle" : {
                        "type" : "constant",
                        "value" : "primary"
                      },
                      "action" : {
                        "type" : "constant",
                        "value" : "Submit task"
                      },
                      "assign" : {
                        "type" : "constant",
                        "value" : false
                      },
                      "url" : {
                        "type" : "interpolation"
                      },
                      "responseStatusCode" : {
                        "type" : "variable",
                        "value" : ""
                      },
                      "dataToSend" : {
                        "type" : "expression",
                        "value" : "selectedCat"
                      },
                      "urlInsert" : {
                        "type" : "constant",
                        "value" : "../API/extension/posgradosRest?url=insertCatPuestoTrabajo"
                      },
                      "urlUpdate" : {
                        "type" : "constant",
                        "value" : "../API/extension/posgradosRest?url=updateCatPuestoTrabajo"
                      },
                      "navigationVar" : {
                        "type" : "variable",
                        "value" : "navigationVar"
                      },
                      "dataToFilter" : {
                        "type" : "variable",
                        "value" : ""
                      },
                      "userData" : {
                        "type" : "variable",
                        "value" : ""
                      }
                    },
                    "reference" : "4c861b37-9974-4428-b991-5cd9e7290b95",
                    "hasValidationError" : false,
                    "id" : "customPSGRBotonGuardarCatV2Ang"
                  }
                ]
              ]
            }
          ]
        ]
      }
    ]
  ],
  "assets" : [
    {
      "id" : "55c44c02-112d-4f72-b86c-5f8105f1b996",
      "name" : "jquery.min (1).js",
      "type" : "js",
      "order" : 2,
      "external" : false
    },
    {
      "id" : "a49f3c6e-5830-493e-a3ab-94c5e6f5aa1e",
      "name" : "sweetalert.min.js",
      "type" : "js",
      "order" : 4,
      "external" : false
    },
    {
      "id" : "7d14b8dd-0f87-4479-8ee4-6922456f99c2",
      "name" : "anahuac_custom_styles (2).css",
      "type" : "css",
      "order" : 1,
      "external" : false
    },
    {
      "id" : "40f29f69-5e1c-4382-bdba-028de76f8337",
      "name" : "localization.json",
      "type" : "json",
      "order" : 0,
      "external" : false
    },
    {
      "id" : "4df2887f-e7c3-43e9-acd3-910af0b724d1",
      "name" : "Header.png",
      "type" : "img",
      "order" : 5,
      "external" : false
    },
    {
      "id" : "2b7923a6-eced-49de-9272-bdfefd877dca",
      "name" : "bootstrap.min (1) (1).js",
      "type" : "js",
      "order" : 3,
      "external" : false
    },
    {
      "id" : "0c85dcc5-83fd-4c03-9ddb-e824757c4b5b",
      "name" : "style.css",
      "type" : "css",
      "order" : 0,
      "external" : false
    }
  ],
  "inactiveAssets" : [ ],
  "variables" : {
    "lstCat" : {
      "type" : "json",
      "value" : [
        "[]"
      ],
      "exposed" : false
    },
    "reload" : {
      "type" : "constant",
      "value" : [
        "false"
      ],
      "exposed" : false
    },
    "selectedCat" : {
      "type" : "json",
      "value" : [
        "{}"
      ],
      "exposed" : false
    },
    "navigationVar" : {
      "type" : "constant",
      "value" : [
        "tabla"
      ],
      "exposed" : false
    },
    "isUpdate" : {
      "type" : "constant",
      "value" : [
        "false"
      ],
      "exposed" : false
    },
    "userData" : {
      "type" : "url",
      "value" : [
        "../API/system/session/1"
      ],
      "advancedOptions" : { },
      "exposed" : false
    }
  },
  "hasValidationError" : false,
  "uuid" : "c06fe76d-a9fd-47e1-a377-d210c3e0061f",
  "type" : "page",
  "description" : "Page generated with Bonita UI designer"
}